db_mimic/__init__.py
db_mimic/create_table.py
db_mimic/db.py
db_mimic/demo_db.py
db_mimic/filter_table.py
db_mimic/helpers.py
db_mimic/select_from_table.py
mock_db-0.0.2.dist-info/METADATA
mock_db-0.0.2.dist-info/WHEEL
mock_db-0.0.2.dist-info/top_level.txt
mock_db-0.0.2.dist-info/RECORD
